setup.py
pyyo/__init__.py
pyyo/yo.py
pyyo.egg-info/PKG-INFO
pyyo.egg-info/SOURCES.txt
pyyo.egg-info/dependency_links.txt
pyyo.egg-info/requires.txt
pyyo.egg-info/top_level.txt