Metadata-Version: 1.0
Name: pyyo
Version: 0.1
Summary: Send yo using python
Home-page: UNKNOWN
Author: fangh
Author-email: gavintofan@gmail.com
License: GPL v2
Keywords: yo
Platform: any
